netsnoop/__init__.py
netsnoop/acm_monitor.py
netsnoop/dashboard.py
netsnoop/enhanced_anomaly_logger.py
netsnoop/setup_runner.py
netsnoop-0.1.4.dist-info/licenses/LICENSE
netsnoop-0.1.4.dist-info/METADATA
netsnoop-0.1.4.dist-info/WHEEL
netsnoop-0.1.4.dist-info/entry_points.txt
netsnoop-0.1.4.dist-info/top_level.txt
netsnoop-0.1.4.dist-info/RECORD
