Metadata-Version: 2.4
Name: netsnoop
Version: 0.1.4
Summary: NetSnoop: Real-Time Linux System Anomaly Monitor and Dashboard
Author: Chitvi Joshi
Author-email: chitvijoshi2646@gmail.com
License: MIT
Classifier: Programming Language :: Python :: 3
Classifier: Operating System :: POSIX :: Linux
Classifier: License :: OSI Approved :: MIT License
Classifier: Intended Audience :: System Administrators
Classifier: Topic :: System :: Monitoring
Requires-Python: >=3.7
License-File: LICENSE
Requires-Dist: streamlit
Requires-Dist: pandas
Requires-Dist: plotly
Dynamic: author
Dynamic: author-email
Dynamic: classifier
Dynamic: description
Dynamic: description-content-type
Dynamic: license
Dynamic: license-file
Dynamic: requires-dist
Dynamic: requires-python
Dynamic: summary
